{
  "formatVersion": 1,
  "database": {
    "version": 2,
    "identityHash": "9e265a062fb0def0d425ffaaab1d16d8",
    "entities": [
      {
        "tableName": "table_players",
        "createSql": "CREATE TABLE IF NOT EXISTS `${TABLE_NAME}` (`id` INTEGER, `sponsor` INTEGER NOT NULL, `tester` INTEGER NOT NULL, `translater` INTEGER NOT NULL, `moderator` INTEGER NOT NULL, `admin` INTEGER NOT NULL, `developer` INTEGER NOT NULL, `skill` INTEGER NOT NULL, `ratingTimeInQuiz` INTEGER NOT NULL, `ratingTimeInChat` INTEGER NOT NULL, `ratingSmsPoints` INTEGER NOT NULL, `ratingCountQuestions` INTEGER NOT NULL, `ratingCountTrueQuestion` INTEGER NOT NULL, `ratingQuiz` INTEGER NOT NULL, `userName` TEXT NOT NULL, PRIMARY KEY(`id`))",
        "fields": [
          {
            "fieldPath": "id",
            "columnName": "id",
            "affinity": "INTEGER",
            "notNull": false
          },
          {
            "fieldPath": "sponsor",
            "columnName": "sponsor",
            "affinity": "INTEGER",
            "notNull": true
          },
          {
            "fieldPath": "tester",
            "columnName": "tester",
            "affinity": "INTEGER",
            "notNull": true
          },
          {
            "fieldPath": "translater",
            "columnName": "translater",
            "affinity": "INTEGER",
            "notNull": true
          },
          {
            "fieldPath": "moderator",
            "columnName": "moderator",
            "affinity": "INTEGER",
            "notNull": true
          },
          {
            "fieldPath": "admin",
            "columnName": "admin",
            "affinity": "INTEGER",
            "notNull": true
          },
          {
            "fieldPath": "developer",
            "columnName": "developer",
            "affinity": "INTEGER",
            "notNull": true
          },
          {
            "fieldPath": "skill",
            "columnName": "skill",
            "affinity": "INTEGER",
            "notNull": true
          },
          {
            "fieldPath": "ratingTimeInQuiz",
            "columnName": "ratingTimeInQuiz",
            "affinity": "INTEGER",
            "notNull": true
          },
          {
            "fieldPath": "ratingTimeInChat",
            "columnName": "ratingTimeInChat",
            "affinity": "INTEGER",
            "notNull": true
          },
          {
            "fieldPath": "ratingSmsPoints",
            "columnName": "ratingSmsPoints",
            "affinity": "INTEGER",
            "notNull": true
          },
          {
            "fieldPath": "ratingCountQuestions",
            "columnName": "ratingCountQuestions",
            "affinity": "INTEGER",
            "notNull": true
          },
          {
            "fieldPath": "ratingCountTrueQuestion",
            "columnName": "ratingCountTrueQuestion",
            "affinity": "INTEGER",
            "notNull": true
          },
          {
            "fieldPath": "ratingQuiz",
            "columnName": "ratingQuiz",
            "affinity": "INTEGER",
            "notNull": true
          },
          {
            "fieldPath": "userName",
            "columnName": "userName",
            "affinity": "TEXT",
            "notNull": true
          }
        ],
        "primaryKey": {
          "autoGenerate": false,
          "columnNames": [
            "id"
          ]
        },
        "indices": [],
        "foreignKeys": []
      },
      {
        "tableName": "chat_data",
        "createSql": "CREATE TABLE IF NOT EXISTS `${TABLE_NAME}` (`id` INTEGER PRIMARY KEY AUTOINCREMENT, `tpovId` INTEGER NOT NULL, `time` TEXT NOT NULL, `user` TEXT NOT NULL, `msg` TEXT NOT NULL, `importance` INTEGER NOT NULL, `icon` TEXT NOT NULL, `rating` INTEGER NOT NULL, `reaction` INTEGER NOT NULL)",
        "fields": [
          {
            "fieldPath": "id",
            "columnName": "id",
            "affinity": "INTEGER",
            "notNull": false
          },
          {
            "fieldPath": "tpovId",
            "columnName": "tpovId",
            "affinity": "INTEGER",
            "notNull": true
          },
          {
            "fieldPath": "time",
            "columnName": "time",
            "affinity": "TEXT",
            "notNull": true
          },
          {
            "fieldPath": "user",
            "columnName": "user",
            "affinity": "TEXT",
            "notNull": true
          },
          {
            "fieldPath": "msg",
            "columnName": "msg",
            "affinity": "TEXT",
            "notNull": true
          },
          {
            "fieldPath": "importance",
            "columnName": "importance",
            "affinity": "INTEGER",
            "notNull": true
          },
          {
            "fieldPath": "icon",
            "columnName": "icon",
            "affinity": "TEXT",
            "notNull": true
          },
          {
            "fieldPath": "rating",
            "columnName": "rating",
            "affinity": "INTEGER",
            "notNull": true
          },
          {
            "fieldPath": "reaction",
            "columnName": "reaction",
            "affinity": "INTEGER",
            "notNull": true
          }
        ],
        "primaryKey": {
          "autoGenerate": true,
          "columnNames": [
            "id"
          ]
        },
        "indices": [],
        "foreignKeys": []
      }
    ],
    "views": [],
    "setupQueries": [
      "CREATE TABLE IF NOT EXISTS room_master_table (id INTEGER PRIMARY KEY,identity_hash TEXT)",
      "INSERT OR REPLACE INTO room_master_table (id,identity_hash) VALUES(42, '9e265a062fb0def0d425ffaaab1d16d8')"
    ]
  }
}